[{"fecha": "01/Feb/2023", "score_general": "10.0", "score_facilidad": "10.0", "materia": "Literatura hispanoamericana contemporánea", "comments": "Barco, Prepárate para leer, InspiracionalCalifica con 2 trabajos cortos sobre 2 lecturas cortas. La asistencia importa, pero es muy tranquilo sacar 10 con ella."}, {"fecha": "08/Ene/2020", "score_general": "10.0", "score_facilidad": "10.0", "materia": "Literatura hispanoamericana contemporánea", "comments": "Prepárate para leer, Tomaría su clase otra vezCalifica con 2 trabajos cortos sobre 2 lecturas cortas. La asistencia importa, pero es muy tranquilo sacar 10 con ella."}, {"fecha": "30/May/2016", "score_general": "10.0", "score_facilidad": "10.0", "materia": "Literatura hispanoamericana contemporánea", "comments": "Califica con 2 trabajos cortos sobre 2 lecturas cortas. La asistencia importa, pero es muy tranquilo sacar 10 con ella."}]